djangocms_video/__init__.py
djangocms_video/cms_plugins.py
djangocms_video/forms.py
djangocms_video/models.py
djangocms_video/locale/af/LC_MESSAGES/django.mo
djangocms_video/locale/af/LC_MESSAGES/django.po
djangocms_video/locale/ar/LC_MESSAGES/django.mo
djangocms_video/locale/ar/LC_MESSAGES/django.po
djangocms_video/locale/be/LC_MESSAGES/django.mo
djangocms_video/locale/be/LC_MESSAGES/django.po
djangocms_video/locale/bg/LC_MESSAGES/django.mo
djangocms_video/locale/bg/LC_MESSAGES/django.po
djangocms_video/locale/bn/LC_MESSAGES/django.mo
djangocms_video/locale/bn/LC_MESSAGES/django.po
djangocms_video/locale/ca/LC_MESSAGES/django.mo
djangocms_video/locale/ca/LC_MESSAGES/django.po
djangocms_video/locale/cmn/LC_MESSAGES/django.mo
djangocms_video/locale/cmn/LC_MESSAGES/django.po
djangocms_video/locale/cs/LC_MESSAGES/django.mo
djangocms_video/locale/cs/LC_MESSAGES/django.po
djangocms_video/locale/cy/LC_MESSAGES/django.mo
djangocms_video/locale/cy/LC_MESSAGES/django.po
djangocms_video/locale/da/LC_MESSAGES/django.mo
djangocms_video/locale/da/LC_MESSAGES/django.po
djangocms_video/locale/de/LC_MESSAGES/django.mo
djangocms_video/locale/de/LC_MESSAGES/django.po
djangocms_video/locale/el/LC_MESSAGES/django.mo
djangocms_video/locale/el/LC_MESSAGES/django.po
djangocms_video/locale/en/LC_MESSAGES/django.mo
djangocms_video/locale/en/LC_MESSAGES/django.po
djangocms_video/locale/es/LC_MESSAGES/django.mo
djangocms_video/locale/es/LC_MESSAGES/django.po
djangocms_video/locale/es_AR/LC_MESSAGES/django.mo
djangocms_video/locale/es_AR/LC_MESSAGES/django.po
djangocms_video/locale/es_BO/LC_MESSAGES/django.mo
djangocms_video/locale/es_BO/LC_MESSAGES/django.po
djangocms_video/locale/es_DO/LC_MESSAGES/django.mo
djangocms_video/locale/es_DO/LC_MESSAGES/django.po
djangocms_video/locale/et/LC_MESSAGES/django.mo
djangocms_video/locale/et/LC_MESSAGES/django.po
djangocms_video/locale/eu/LC_MESSAGES/django.mo
djangocms_video/locale/eu/LC_MESSAGES/django.po
djangocms_video-3.1.0.dist-info/LICENSE
djangocms_video-3.1.0.dist-info/METADATA
djangocms_video-3.1.0.dist-info/WHEEL
djangocms_video-3.1.0.dist-info/top_level.txt
djangocms_video-3.1.0.dist-info/RECORD
